pipepermcalc/__init__.py
pipepermcalc/pipe.py
pipepermcalc/segment.py
pipepermcalc/database/__init__.py
pipepermcalc/database/ppc_database.csv
pipepermcalc-0.9.0.dist-info/LICENSE
pipepermcalc-0.9.0.dist-info/METADATA
pipepermcalc-0.9.0.dist-info/WHEEL
pipepermcalc-0.9.0.dist-info/top_level.txt
pipepermcalc-0.9.0.dist-info/RECORD
